comet/__init__.py
comet/__main__.py
comet/cli.py
comet/file_utils.py
comet/metrics/__init__.py
comet/metrics/constants.py
comet/metrics/convective_triggering.py
comet/metrics/coupling_indices.py
comet/metrics/heated_condensation.py
comet/metrics/mixing_diagram.py
comet/metrics/utils.py
comet/metrics/fortran/__init__.py
comet/metrics/fortran/ctp_hilow.f90
comet/metrics/fortran/hcfcalc.f90
comet/metrics/fortran/rh_tendency.f90
coupling_metrics-1.0.0.dist-info/AUTHORS.rst
coupling_metrics-1.0.0.dist-info/LICENSE
coupling_metrics-1.0.0.dist-info/METADATA
coupling_metrics-1.0.0.dist-info/WHEEL
coupling_metrics-1.0.0.dist-info/entry_points.txt
coupling_metrics-1.0.0.dist-info/top_level.txt
coupling_metrics-1.0.0.dist-info/RECORD
