Metadata-Version: 2.1
Name: coupling-metrics
Version: 1.0.0
Summary: Calculate various state-of-the-art land-atmosphere coupling metrics
Home-page: https://github.com/abtawfik/coupling-metrics
Author: Ahmed Tawfik
Author-email: abtawfik@umich.edu
License: MIT License
Project-URL: Documentation, https://coupling-metrics.readthedocs.io/
Project-URL: Changelog, https://coupling-metrics.readthedocs.io/en/latest/changelog.html
Project-URL: Issue Tracker, https://github.com/abtawfik/coupling-metrics/issues
Platform: UNKNOWN
Classifier: Development Status :: 5 - Production/Stable
Classifier: Intended Audience :: Developers
Classifier: Operating System :: Unix
Classifier: Operating System :: POSIX
Classifier: Operating System :: Microsoft :: Windows
Classifier: Programming Language :: Python
Classifier: Programming Language :: Python :: 3
Classifier: Programming Language :: Python :: 3.5
Classifier: Programming Language :: Python :: 3.6
Classifier: Programming Language :: Python :: 3.7
Classifier: Programming Language :: Python :: 3.8
Classifier: Programming Language :: Python :: Implementation :: CPython
Classifier: Programming Language :: Python :: Implementation :: PyPy
Requires-Python: >=3.*
Requires-Dist: click
Requires-Dist: xarray
Requires-Dist: dask[complete]
Requires-Dist: toolz
Requires-Dist: numpy
Requires-Dist: netcdf4
Requires-Dist: cfgrib
